weac/__init__.py
weac/constants.py
weac/logging_config.py
weac/analysis/__init__.py
weac/analysis/analyzer.py
weac/analysis/criteria_evaluator.py
weac/analysis/plotter.py
weac/components/__init__.py
weac/components/config.py
weac/components/criteria_config.py
weac/components/layer.py
weac/components/model_input.py
weac/components/scenario_config.py
weac/components/segment.py
weac/core/__init__.py
weac/core/eigensystem.py
weac/core/field_quantities.py
weac/core/scenario.py
weac/core/slab.py
weac/core/slab_touchdown.py
weac/core/system_model.py
weac/core/unknown_constants_solver.py
weac/utils/__init__.py
weac/utils/geldsetzer.py
weac/utils/misc.py
weac/utils/snow_types.py
weac/utils/snowpilot_parser.py
weac-3.0.1.dist-info/licenses/LICENSE
weac-3.0.1.dist-info/METADATA
weac-3.0.1.dist-info/WHEEL
weac-3.0.1.dist-info/top_level.txt
weac-3.0.1.dist-info/RECORD
