Metadata-Version: 2.4
Name: weac
Version: 3.0.1
Summary: Weak layer anticrack nucleation model
Author-email: 2phi GbR <mail@2phi.de>
License-Expression: MIT
Project-URL: Homepage, https://github.com/2phi/weac
Project-URL: Demo, https://github.com/2phi/weac/blob/main/demo/demo.ipynb
Project-URL: Documentation, https://2phi.github.io/weac
Project-URL: Issues and feature requests, https://github.com/2phi/weac/issues
Classifier: Programming Language :: Python :: 3
Classifier: Programming Language :: Python :: 3.12
Classifier: Programming Language :: Python :: 3.13
Classifier: Operating System :: OS Independent
Classifier: Topic :: Scientific/Engineering
Requires-Python: >=3.12
License-File: LICENSE
Requires-Dist: matplotlib>=3.9.1
Requires-Dist: numpy>=2.0.1
Requires-Dist: scipy>=1.14.0
Requires-Dist: pydantic>=2.11.7
Requires-Dist: snowpylot>=1.1.3
Provides-Extra: interactive
Requires-Dist: jupyter; extra == "interactive"
Requires-Dist: ipython>=8.37.0; extra == "interactive"
Requires-Dist: ipykernel>=6.30.1; extra == "interactive"
Requires-Dist: jupyter_client>=8.6.3; extra == "interactive"
Requires-Dist: jupyter_core>=5.8.1; extra == "interactive"
Requires-Dist: matplotlib-inline>=0.1.7; extra == "interactive"
Requires-Dist: nest-asyncio>=1.6.0; extra == "interactive"
Requires-Dist: pyzmq>=27.0.1; extra == "interactive"
Requires-Dist: tornado>=6.5.2; extra == "interactive"
Requires-Dist: traitlets>=5.14.3; extra == "interactive"
Provides-Extra: docs
Requires-Dist: sphinx; extra == "docs"
Requires-Dist: sphinxawesome-theme; extra == "docs"
Provides-Extra: dev
Requires-Dist: nbclient>=0.10.0; extra == "dev"
Requires-Dist: nbconvert>=7.16.4; extra == "dev"
Requires-Dist: nbformat>=5.10.0; extra == "dev"
Requires-Dist: jupyter; extra == "dev"
Requires-Dist: ipython>=8.37.0; extra == "dev"
Requires-Dist: ipykernel>=6.30.1; extra == "dev"
Requires-Dist: jupyter_client>=8.6.3; extra == "dev"
Requires-Dist: jupyter_core>=5.8.1; extra == "dev"
Requires-Dist: matplotlib-inline>=0.1.7; extra == "dev"
Requires-Dist: nest-asyncio>=1.6.0; extra == "dev"
Requires-Dist: pyzmq>=27.0.1; extra == "dev"
Requires-Dist: tornado>=6.5.2; extra == "dev"
Requires-Dist: traitlets>=5.14.3; extra == "dev"
Requires-Dist: ruff>=0.4.0; extra == "dev"
Requires-Dist: pylint>=3.2.0; extra == "dev"
Requires-Dist: pycodestyle>=2.11.1; extra == "dev"
Requires-Dist: black>=24.4.0; extra == "dev"
Requires-Dist: isort>=5.13.0; extra == "dev"
Requires-Dist: bump-my-version; extra == "dev"
Requires-Dist: build; extra == "dev"
Dynamic: license-file
